desc/__init__.py
desc/__main__.py
desc/_version.py
desc/backend.py
desc/basis.py
desc/batching.py
desc/coils.py
desc/compat.py
desc/continuation.py
desc/derivatives.py
desc/grid.py
desc/input_reader.py
desc/interpolate.py
desc/nestor.py
desc/optimizable.py
desc/perturbations.py
desc/plotting.py
desc/profiles.py
desc/random.py
desc/transform.py
desc/utils.py
desc/vmec.py
desc/vmec_utils.py
desc/compute/__init__.py
desc/compute/_basis_vectors.py
desc/compute/_bootstrap.py
desc/compute/_core.py
desc/compute/_curve.py
desc/compute/_equil.py
desc/compute/_fast_ion.py
desc/compute/_field.py
desc/compute/_geometry.py
desc/compute/_metric.py
desc/compute/_neoclassical.py
desc/compute/_old.py
desc/compute/_omnigenity.py
desc/compute/_profiles.py
desc/compute/_stability.py
desc/compute/_surface.py
desc/compute/data_index.py
desc/compute/utils.py
desc/equilibrium/__init__.py
desc/equilibrium/coords.py
desc/equilibrium/equilibrium.py
desc/equilibrium/initial_guess.py
desc/equilibrium/utils.py
desc/examples/ARIES-CS_output.h5
desc/examples/ATF_output.h5
desc/examples/DSHAPE_CURRENT_output.h5
desc/examples/DSHAPE_output.h5
desc/examples/ESTELL_output.h5
desc/examples/HELIOTRON_output.h5
desc/examples/HSX_output.h5
desc/examples/NCSX_output.h5
desc/examples/SOLOVEV_output.h5
desc/examples/W7-X_output.h5
desc/examples/WISTELL-A_output.h5
desc/examples/__init__.py
desc/examples/precise_QA.py
desc/examples/precise_QA_output.h5
desc/examples/precise_QH.py
desc/examples/precise_QH_output.h5
desc/examples/reactor_QA.py
desc/examples/reactor_QA_output.h5
desc/examples/regenerate_all_equilibria.py
desc/external/__init__.py
desc/external/_terpsichore.py
desc/geometry/__init__.py
desc/geometry/core.py
desc/geometry/curve.py
desc/geometry/surface.py
desc/integrals/__init__.py
desc/integrals/_bounce_utils.py
desc/integrals/_interp_utils.py
desc/integrals/basis.py
desc/integrals/bounce_integral.py
desc/integrals/quad_utils.py
desc/integrals/singularities.py
desc/integrals/surface_integral.py
desc_opt-0.16.0.dist-info/licenses/LICENSE
desc_opt-0.16.0.dist-info/METADATA
desc_opt-0.16.0.dist-info/WHEEL
desc_opt-0.16.0.dist-info/entry_points.txt
desc_opt-0.16.0.dist-info/top_level.txt
desc_opt-0.16.0.dist-info/RECORD
