Metadata-Version: 2.4
Name: desc-opt
Version: 0.16.0
Summary: Computes, analyzes and optimizes 3D MHD equilibria for stellarators and tokamaks
Home-page: https://github.com/PlasmaControl/DESC/
Author: Daniel Dudt, Rory Conlin, Dario Panici, Kaya Unalmis, Yigit Gunsur Elmacioglu, Rahul Gaur, Patrick Kim, Egemen Kolemen
Author-email: PlasmaControl@princeton.edu
License: MIT
Project-URL: Issues Tracker, https://github.com/PlasmaControl/DESC/issues
Project-URL: Contributing, https://github.com/PlasmaControl/DESC/blob/master/CONTRIBUTING.rst
Project-URL: Source Code, https://github.com/PlasmaControl/DESC/
Project-URL: Documentation, https://desc-docs.readthedocs.io/
Keywords: stellarator tokamak equilibrium perturbation mhd magnetohydrodynamics stability confinement plasma physics optimization design fusion
Classifier: Development Status :: 3 - Alpha
Classifier: Intended Audience :: Science/Research
Classifier: License :: OSI Approved :: MIT License
Classifier: Natural Language :: English
Classifier: Programming Language :: Python :: 3
Classifier: Programming Language :: Python :: 3.10
Classifier: Programming Language :: Python :: 3.11
Classifier: Programming Language :: Python :: 3.12
Classifier: Programming Language :: Python :: 3.13
Classifier: Topic :: Scientific/Engineering
Classifier: Topic :: Scientific/Engineering :: Mathematics
Classifier: Topic :: Scientific/Engineering :: Physics
Classifier: Topic :: Scientific/Engineering :: Visualization
Requires-Python: >=3.10
License-File: LICENSE
Requires-Dist: jax!=0.5.1,!=0.5.2,!=0.6.0,!=0.7.1,<0.8.0,>=0.5.0
Requires-Dist: colorama<=0.4.6
Requires-Dist: diffrax<=0.7.0,>=0.6.0
Requires-Dist: h5py<=3.15.1,>=3.0.0
Requires-Dist: interpax<=0.3.12,>=0.3.3
Requires-Dist: jax-finufft>=1.1.0
Requires-Dist: matplotlib<=3.10.7,>=3.7.3
Requires-Dist: mpmath<=1.3.0,>=1.0.0
Requires-Dist: netcdf4<=1.7.3,>=1.5.4
Requires-Dist: numpy<=2.2.6,>=1.20.0
Requires-Dist: nvgpu<=0.10.0
Requires-Dist: orthax<=0.2.6
Requires-Dist: plotly<=6.4.0,>=5.16
Requires-Dist: psutil<=7.1.3
Requires-Dist: pylatexenc<=2.10,>=2.0
Requires-Dist: quadax<=0.2.11,>=0.2.2
Requires-Dist: scikit-image<=0.25.2
Requires-Dist: scipy<=1.15.3,>=1.7.0
Requires-Dist: sympy
Requires-Dist: termcolor<=3.2.0
Dynamic: author
Dynamic: author-email
Dynamic: classifier
Dynamic: description
Dynamic: description-content-type
Dynamic: home-page
Dynamic: keywords
Dynamic: license
Dynamic: license-file
Dynamic: project-url
Dynamic: requires-dist
Dynamic: requires-python
Dynamic: summary
